Verilog/bcd_7seg_dpver/BCDto7seg_dataflow.v
module BCD2 (
    input A,B,C,D, //A MSB
    output a,b,c,d,e,f,g,dp
);

//共陽

assign dp= 1'b1;
assign a = (B & ~C & ~D) | (~A & ~B & ~C & D);
assign b = (B & ~C & D) | (B & C & ~D);
assign c = ~B & C & ~D;
assign d = (B & ~C & ~D) | (B & C & D) | (~A & ~B & ~C & D);
assign e = D | (B & ~C);
assign f = (C & D) | (~B & C) | (~A & ~B & D);
assign g = (~A & ~B & ~C) | (B & C & D);


//共陰
/*
assign dp=1'b0;
assign a = ~((B & ~C & ~D) | (~A & ~B & ~C & D));
assign b = ~((B & ~C & D) | (B & C & ~D));
assign c = ~(~B & C & ~D);
assign d = ~((B & ~C & ~D) | (B & C & D) | (~A & ~B & ~C & D));
assign e = ~(D | (B & ~C));
assign f = ~((C & D) | (~B & C) | (~A & ~B & D));
assign g = ~((~A & ~B & ~C) | (B & C & D));
*/
endmodule

Verilog/bcd_7seg_dpver/bcd_7seg_tb.v
module bcd_7seg_tb;

reg A,B,C,D;
wire a,b,c,d,e,f,g,dp;

//BCD1 BCD( .A(A), .B(B), .C(C), .D(D), .a(a), .b(b), .c(c), .d(d), .e(e), .f(f), .g(g), .dp(dp));//gate level
BCD2 BCD( .A(A), .B(B), .C(C), .D(D), .a(a), .b(b), .c(c), .d(d), .e(e), .f(f), .g(g), .dp(dp)); //dataflow
initial 
begin
 A = 0; B = 0; C = 0; D = 0;
 #10;
 A = 0; B = 0; C = 0; D = 1;
 #10;
 A = 0; B = 0; C = 1; D = 0;
 #10;
 A = 0; B = 0; C = 1; D = 1;
 #10;
 A = 0; B = 1; C = 0; D = 0;
 #10;
 A = 0; B = 1; C = 0; D = 1;
 #10;
 A = 0; B = 1; C = 1; D = 0;
 #10;
 A = 0; B = 1; C = 1; D = 1;
 #10;
 A = 1; B = 0; C = 0; D = 0;
 #10;
 A = 1; B = 0; C = 0; D = 1;
 #10;
end

initial begin
    $dumpfile("wave.vcd"); //iverilog -o wave BCDto7seg_gatelevel.v bcd_7seg_tb.v //iverilog -o wave BCDto7seg_dataflow.v bcd_7seg_tb.v
    $dumpvars(0, bcd_7seg_tb); //vvp wave
end
endmodule

Verilog/bcd_7seg_dpver/wave.vcd
$date
	Thu Oct 30 14:46:47 2025
$end
$version
	Icarus Verilog
$end
$timescale
	1s
$end
$scope module bcd_7seg_tb $end
$var wire 1 ! dp $end
$var wire 1 " g $end
$var wire 1 # f $end
$var wire 1 $ e $end
$var wire 1 % d $end
$var wire 1 & c $end
$var wire 1 ' b $end
$var wire 1 ( a $end
$var reg 1 ) A $end
$var reg 1 * B $end
$var reg 1 + C $end
$var reg 1 , D $end
$scope module BCD $end
$var wire 1 ) A $end
$var wire 1 * B $end
$var wire 1 + C $end
$var wire 1 , D $end
$var wire 1 ( a $end
$var wire 1 ' b $end
$var wire 1 & c $end
$var wire 1 % d $end
$var wire 1 ! dp $end
$var wire 1 $ e $end
$var wire 1 # f $end
$var wire 1 " g $end
$upscope $end
$upscope $end
$enddefinitions $end
$comment Show the parameter values. $end
$dumpall
$end
#0
$dumpvars
0,
0+
0*
0)
1(
1'
1&
1%
1$
1#
0"
0!
$end
#10
0(
0%
0#
0$
1,
#20
1"
1(
1%
0&
1$
0,
1+
#30
1&
0$
1,
#40
0%
0(
1#
0$
0,
0+
1*
#50
1%
1(
0'
1,
#60
1$
0,
1+
#70
1'
0%
0#
0"
0$
1,
#80
1%
1#
1"
1$
0,
0+
0*
1)
#90
0$
1,
