Verilog/ex1_1015/encoder_8to3.v
module encoder_8to3 (
    input [7:0] I,
    output [2:0] y
);
assign y[2] = | I[7:4];
assign y[1] = I[7] | I[6] | I[3] | I[2];
assign y[0] = I[7] | I[5] | I[3] | I[1];

endmodule

Verilog/ex1_1015/tb.v
module tb;
reg [7:0] I;
wire [2:0] y;
encoder_8to3 enc(.y(y), .I(I));
initial begin
    I = 8'B00000001;
    #10;
    I = 8'B00000010;
    #10;
    I = 8'B00000100;
    #10;
    I = 8'B00001000;
    #10;
    I = 8'B00010000;
    #10;
    I = 8'B00100000;
    #10;
    I = 8'B01000000;
    #10;
    I = 8'B10000000;
    #10;$finish;
end
initial begin
    $dumpfile("wave.vcd"); //  iverilog -o wave encoder_8to3.v tb.v
    $dumpvars(0, tb); // vvp wave
end
endmodule

Verilog/ex1_1015/wave.vcd
$date
	Wed Oct 15 14:18:54 2025
$end
$version
	Icarus Verilog
$end
$timescale
	1s
$end
$scope module tb $end
$var wire 3 ! y [2:0] $end
$var reg 8 " I [7:0] $end
$scope module enc $end
$var wire 8 # I [7:0] $end
$var wire 3 $ y [2:0] $end
$upscope $end
$upscope $end
$enddefinitions $end
$comment Show the parameter values. $end
$dumpall
$end
#0
$dumpvars
b0 $
b1 #
b1 "
b0 !
$end
#10
b1 !
b1 $
b10 "
b10 #
#20
b10 !
b10 $
b100 "
b100 #
#30
b11 !
b11 $
b1000 "
b1000 #
#40
b100 !
b100 $
b10000 "
b10000 #
#50
b101 !
b101 $
b100000 "
b100000 #
#60
b110 !
b110 $
b1000000 "
b1000000 #
#70
b111 !
b111 $
b10000000 "
b10000000 #
