Verilog/bch_7seg_dpver/BCHto7seg_gatelevel.v
module BCD1(a,b,c,d,e,f,g,dp,A,B,C,D);//A MSB
output a,b,c,d,e,f,g,dp;
input A,B,C,D;
wire an,bn,cn,dn,adn,bc,anc,bndn,anbd,anbn,acnd,ancd,ancndn,anb,cnd,bnd,bncn,abnd,abdn,ancdn,bncd
    ,bncndn,ac,ab,abn,ad,cdn,bnc,bcnd,anbdn,bdn,cndn,anbcn,abncn,ao,bo,co,do,eo,fo,go;
not n1(an,A);
not n2(bn,B);
not n3(cn,C);
not n4(dn,D);
and (adn,A,dn);//a
and (bc,B,C);
and (anc,an,C);
and (bndn,bn,dn);
and (anbd,an,B,D);
and (abncn,A,bn,cn);
and(bndn,bn,dn);//b
and(anbn,an,bn);
and(acnd,A,cn,D);
and(ancd,an,C,D);
and(ancndn,an,cn,dn);
and(abn,A,bn);//c
and(anb,an,B);
and(cnd,cn,D);
and(bnd,bn,D);
and(bncn,bn,cn);
and(abnd,A,bn,D);//d
and(abdn,A,B,dn);
and(bcnd,B,cn,D);
and(ancdn,an,C,dn);
and(bncd,bn,C,D);
and(bncndn,bn,cn,dn);
and(ac,A,C);//e
and(ab,A,B);
and(cdn,C,dn);
and(bndn,bn,dn);
and(abn,A,bn);//f
and(ac,A,C);
and(bdn,B,dn);
and(cndn,cn,dn);
and(anbcn,an,B,cn);
and(abn,A,bn);//g
and(ad,A,D);
and(cdn,C,dn);
and(bnc,bn,C);
and(bcnd,B,cn,D);
and(anbdn,an,B,dn);
or a1(ao,adn,bc,anc,bndn,anbd,abncn);//  adn+bc+anc+bndn+anbd+abncn
or b1(bo,bndn,anbn,acnd,ancd,ancndn);//bndn+anbn+acnd+ancd+ancndn
or c1(co,abn,anb,cnd,bnd,bncn);// abn+anb+cnd+bnd+bncn
or d1(do,abnd,abdn,bcnd,ancdn,bncd,bncndn); //abnd+abdn+bcnd+ancdn+bncd+bncndn
or e1(eo,ac,ab,cdn,bndn);// ac+ab+cdn+bndn
or f1(fo,abn,ac,bdn,cndn,anbcn);//abn+ac+bdn+cndn+anbcn
or g1(go,abn,ad,cdn,bnc,bcnd,anbdn);// abn+ad+cdn+bnc+bcnd+anbdn
//共陰
/*
or a2(a,ao,0);
or b2(b,bo,0);
or c2(c,co,0);
or d2(d,d0,0);
or e2(e,e0,0);
or f2(f,f0,0);
or g2(g,go,0);
or dp1(dp,0,0);
*/
//共陽
not(a,ao);
not(b,bo);
not(c,co);
not(d,do);
not(e,eo);
not(f,fo);
not(g,go);
or dp1(dp,1,0);
endmodule

Verilog/bch_7seg_dpver/bch_7seg_tb.v
module bcd_7seg_tb;

reg A,B,C,D;
wire a,b,c,d,e,f,g,dp; //gate dataflow
//wire [7:0] out;; //behavior
BCD1 BCD( .A(A), .B(B), .C(C), .D(D), .a(a), .b(b), .c(c), .d(d), .e(e), .f(f), .g(g), .dp(dp));//gate level
//BCD2 BCD( .A(A), .B(B), .C(C), .D(D), .a(a), .b(b), .c(c), .d(d), .e(e), .f(f), .g(g), .dp(dp)); //dataflow
//BCD3 BCD( .A(A), .B(B), .C(C), .D(D), .out(out)); //behavior
initial 
begin
 A = 0; B = 0; C = 0; D = 0;
 #10;
 A = 0; B = 0; C = 0; D = 1;
 #10;
 A = 0; B = 0; C = 1; D = 0;
 #10;
 A = 0; B = 0; C = 1; D = 1;
 #10;
 A = 0; B = 1; C = 0; D = 0;
 #10;
 A = 0; B = 1; C = 0; D = 1;
 #10;
 A = 0; B = 1; C = 1; D = 0;
 #10;
 A = 0; B = 1; C = 1; D = 1;
 #10;
 A = 1; B = 0; C = 0; D = 0;
 #10;
 A = 1; B = 0; C = 0; D = 1;
 #10;
 A = 1; B = 0; C = 1; D = 0;
 #10;
 A = 1; B = 0; C = 1; D = 1;
 #10
 A = 1; B = 1; C = 0; D = 0;
 #10;
 A = 1; B = 1; C = 0; D = 1;
 #10;
 A = 1; B = 1; C = 1; D = 0;
 #10;
 A = 1; B = 1; C = 1; D = 1;
 #10;
end

initial begin
    $dumpfile("wave.vcd"); //iverilog -o wave BCHto7seg_gatelevel.v bch_7seg_tb.v 
    $dumpvars(0, bcd_7seg_tb); //vvp wave
end
endmodule

Verilog/bch_7seg_dpver/wave.vcd
$date
	Sun Nov 02 21:37:20 2025
$end
$version
	Icarus Verilog
$end
$timescale
	1s
$end
$scope module bcd_7seg_tb $end
$var wire 1 ! g $end
$var wire 1 " f $end
$var wire 1 # e $end
$var wire 1 $ dp $end
$var wire 1 % d $end
$var wire 1 & c $end
$var wire 1 ' b $end
$var wire 1 ( a $end
$var reg 1 ) A $end
$var reg 1 * B $end
$var reg 1 + C $end
$var reg 1 , D $end
$scope module BCD $end
$var wire 1 ) A $end
$var wire 1 * B $end
$var wire 1 + C $end
$var wire 1 , D $end
$var wire 1 ( a $end
$var wire 1 - ab $end
$var wire 1 . abdn $end
$var wire 1 / abn $end
$var wire 1 0 abncn $end
$var wire 1 1 abnd $end
$var wire 1 2 ac $end
$var wire 1 3 acnd $end
$var wire 1 4 ad $end
$var wire 1 5 adn $end
$var wire 1 6 an $end
$var wire 1 7 anb $end
$var wire 1 8 anbcn $end
$var wire 1 9 anbd $end
$var wire 1 : anbdn $end
$var wire 1 ; anbn $end
$var wire 1 < anc $end
$var wire 1 = ancd $end
$var wire 1 > ancdn $end
$var wire 1 ? ancndn $end
$var wire 1 @ ao $end
$var wire 1 ' b $end
$var wire 1 A bc $end
$var wire 1 B bcnd $end
$var wire 1 C bdn $end
$var wire 1 D bn $end
$var wire 1 E bnc $end
$var wire 1 F bncd $end
$var wire 1 G bncn $end
$var wire 1 H bncndn $end
$var wire 1 I bnd $end
$var wire 1 J bndn $end
$var wire 1 K bo $end
$var wire 1 & c $end
$var wire 1 L cdn $end
$var wire 1 M cn $end
$var wire 1 N cnd $end
$var wire 1 O cndn $end
$var wire 1 P co $end
$var wire 1 % d $end
$var wire 1 Q dn $end
$var wire 1 R do $end
$var wire 1 $ dp $end
$var wire 1 # e $end
$var wire 1 S eo $end
$var wire 1 " f $end
$var wire 1 T fo $end
$var wire 1 ! g $end
$var wire 1 U go $end
$upscope $end
$upscope $end
$enddefinitions $end
$comment Show the parameter values. $end
$dumpall
$end
#0
$dumpvars
0U
1T
1S
1R
1Q
1P
1O
0N
1M
0L
1K
1J
0I
1H
1G
0F
0E
1D
0C
0B
0A
1@
1?
0>
0=
0<
1;
0:
09
08
07
16
05
04
03
02
01
00
0/
0.
0-
0,
0+
0*
0)
0(
0'
0&
0%
1$
0#
0"
1!
$end
#10
1%
1(
1"
0R
0@
1#
0T
0S
0?
0H
0J
0O
0Q
1N
1I
1,
#20
0%
1R
0#
1&
0(
0!
1S
0P
1@
1U
1>
1J
1L
0G
1Q
0N
0I
0M
1<
1E
0,
1+
#30
1#
0&
0S
1P
0>
0J
0L
0Q
1=
1I
1F
1,
#40
0"
1T
1(
0'
1%
0!
0@
1K
0R
1U
1C
1:
1?
1O
18
0;
1Q
0I
1M
0<
0=
0F
0E
0D
17
0,
0+
1*
#50
1'
0K
0(
0%
1@
1R
0?
0C
0O
0:
0Q
19
1N
1B
1,
#60
0#
0%
0!
1S
1R
1U
1>
1C
1L
1:
08
1Q
09
0N
0B
0M
1A
1<
0,
1+
#70
1%
1"
1!
0R
0T
1#
0U
0'
0S
1K
0>
0C
0L
0:
0Q
19
1=
1,
#80
0%
0"
0!
1R
0#
1T
1U
0(
0&
1S
1@
1P
15
1O
10
1G
1H
1J
1/
1Q
1M
0<
0=
1D
0A
09
07
06
0,
0+
0*
1)
#90
1#
0S
05
0H
0J
0O
0Q
13
1N
1I
11
14
1,
#100
0'
1%
1K
0R
0#
15
1J
1L
00
0G
1S
1Q
03
0N
0I
01
04
0M
12
1E
0,
1+
#110
1(
1'
0@
0K
0%
1R
05
0J
0L
0Q
1I
11
1F
14
1,
#120
0(
1@
1&
0%
0"
1!
0P
1R
1T
0U
15
1.
1C
1O
0/
1Q
0I
01
04
1M
0F
02
0E
0D
1-
0,
0+
1*
#130
1(
1"
0@
0T
0'
0&
0!
1K
1P
1U
05
0.
0C
0O
0Q
13
1N
14
1B
1,
#140
1'
1&
0%
0!
0(
0"
0K
0P
1R
1U
1@
1T
15
1.
1C
1L
1Q
03
0N
04
0B
0M
1A
12
0,
1+
#150
1%
0R
05
0.
0C
0L
0Q
14
1,
