Verilog/midterm_2/behavior.v
module circuit (
    output reg f,
    input w,x,y,z
);
reg b, c, d, e;
always @(*) begin
    b = (x == 0 || w == 0)?1:0;
    c = (w == 1 || y == 0)?1:0;
    d = (b == 0 || c == 0)?1:0;
    e = (w == 0 || z == 0)?1:0;
    f = (d == 0 || e == 0)?1:0;
end

endmodule

Verilog/midterm_2/tb.v
module tb;
wire f;
reg w,x,y,z;
circuit c(f,w,x,y,z);
initial begin
    w = 0;x = 0;y = 0;z = 0;
    for(integer i = 0; i<16; i++)
    begin
        #10;
        {w,x,y,z} ++;
    end
    $finish;
end
initial begin
    $dumpfile("wave.vcd"); //  iverilog -o wave behavior.v tb.v
    $dumpvars(0, tb); // vvp wave
end
endmodule

Verilog/midterm_2/wave.vcd
$date
	Wed Nov 26 14:39:23 2025
$end
$version
	Icarus Verilog
$end
$timescale
	1s
$end
$scope module tb $end
$var wire 1 ! f $end
$var reg 1 " w $end
$var reg 1 # x $end
$var reg 1 $ y $end
$var reg 1 % z $end
$scope module c $end
$var wire 1 " w $end
$var wire 1 # x $end
$var wire 1 $ y $end
$var wire 1 % z $end
$var reg 1 & b $end
$var reg 1 ' c $end
$var reg 1 ( d $end
$var reg 1 ) e $end
$var reg 1 ! f $end
$upscope $end
$scope begin $ivl_for_loop0 $end
$var integer 32 * i [31:0] $end
$upscope $end
$upscope $end
$enddefinitions $end
$comment Show the parameter values. $end
$dumpall
$end
#0
$dumpvars
b0 *
1)
0(
1'
1&
0%
0$
0#
0"
1!
$end
#10
b1 *
1%
#20
0!
1(
0'
b10 *
1$
0%
#30
b11 *
1%
#40
1!
0(
1'
b100 *
1#
0$
0%
#50
b101 *
1%
#60
0!
1(
0'
b110 *
1$
0%
#70
b111 *
1%
#80
1!
0(
1'
b1000 *
1"
0#
0$
0%
#90
0)
b1001 *
1%
#100
1)
b1010 *
1$
0%
#110
0)
b1011 *
1%
#120
0!
1)
1(
0&
b1100 *
1#
0$
0%
#130
1!
0)
b1101 *
1%
#140
0!
1)
b1110 *
1$
0%
#150
1!
0)
b1111 *
1%
#160
1)
0(
1&
b10000 *
0"
0#
0$
0%
