Verilog/ex2_1022/ex2.v
module ALU_func (
    output reg [12:0] result, 
    output reg status,
    input [12:0] x ,y,
    input [2:0] opcode,
    input aclk
);
always@(posedge aclk)
begin
    case (opcode)
        3'b000: result = x;
        3'b001: result = x + y;
        3'b010: result = x - y;
        3'b011: result = x / y;
        3'b100: result = x % y;
        3'b101: result = (x > y);
        3'b110: result = x >> 1;
        3'b111: result = x << 1;
        default: result = 13'hx;
    endcase
    if(result == 0)
        status = 1;
    else 
        status = 0;
end
endmodule

Verilog/ex2_1022/tb.v
module tb;
wire [12:0] result;
wire status;
reg [12:0] x ,y;
reg [2:0] opcode;
reg aclk;
ALU_func alu(.result(result), .status(status), .x(x), .y(y), .opcode(opcode), .aclk(aclk));
initial begin
    x = 4; y =2; opcode = 7; aclk = 0;
    for(integer i = 0;i <8;i = i + 1)
    begin
        opcode = opcode +1;
        #10;
    end
    #80 $finish;
end
always #5 aclk = ~aclk;
initial begin
    $dumpfile("wave.vcd"); //  iverilog -o wave ex2.v tb.v
    $dumpvars(0, tb); // vvp wave
end
endmodule

Verilog/ex2_1022/wave.vcd
$date
	Wed Oct 22 20:38:04 2025
$end
$version
	Icarus Verilog
$end
$timescale
	1s
$end
$scope module tb $end
$var wire 1 ! status $end
$var wire 13 " result [12:0] $end
$var reg 1 # aclk $end
$var reg 3 $ opcode [2:0] $end
$var reg 13 % x [12:0] $end
$var reg 13 & y [12:0] $end
$scope module alu $end
$var wire 1 # aclk $end
$var wire 3 ' opcode [2:0] $end
$var wire 13 ( x [12:0] $end
$var wire 13 ) y [12:0] $end
$var reg 13 * result [12:0] $end
$var reg 1 ! status $end
$upscope $end
$scope begin $ivl_for_loop0 $end
$var integer 32 + i [31:0] $end
$upscope $end
$upscope $end
$enddefinitions $end
$comment Show the parameter values. $end
$dumpall
$end
#0
$dumpvars
b0 +
bx *
b10 )
b100 (
b1 '
b10 &
b100 %
b1 $
0#
bx "
x!
$end
#5
0!
b110 "
b110 *
1#
#10
0#
b10 $
b10 '
b1 +
#15
b10 "
b10 *
1#
#20
0#
b11 $
b11 '
b10 +
#25
1#
#30
0#
b100 $
b100 '
b11 +
#35
1!
b0 "
b0 *
1#
#40
0#
b101 $
b101 '
b100 +
#45
0!
b1 "
b1 *
1#
#50
0#
b110 $
b110 '
b101 +
#55
b10 "
b10 *
1#
#60
0#
b111 $
b111 '
b110 +
#65
b1000 "
b1000 *
1#
#70
0#
b0 $
b0 '
b111 +
#75
b100 "
b100 *
1#
#80
0#
b1000 +
