Verilog/midterm_ex5/c.v
module func(
 input w,x,y,z,
 output f
);
wire wn,xn,yn,zn,a,b,c;
not w0(wn,w);
not x0(xn,x);
not y0(yn,y);
not z0(zn,z);
and a0(a,wn,yn,zn);
and b0(b,x,z);
and c0(c,w,xn,yn);
or d0(f,a,b,c);
endmodule

Verilog/midterm_ex5/tb.v
module tb;
reg x,y,w,z;
wire f;
func F(.f(f), .w(w), .x(x), .y(y), .z(z));
initial begin
    w=0;x=0;y=0;z=0;
    #10;
    w=0;x=0;y=0;z=1;
    #10;
    w=0;x=0;y=1;z=0;
    #10;
    w=0;x=0;y=1;z=1;
    #10;
    w=0;x=1;y=0;z=0;
    #10;
    w=0;x=1;y=0;z=1;
    #10;
    w=0;x=1;y=1;z=0;
    #10;
    w=0;x=1;y=1;z=1;
    #10;
    w=1;x=0;y=0;z=0;
    #10;
    w=1;x=0;y=0;z=1;
    #10;
    w=1;x=0;y=1;z=0;
    #10;
    w=1;x=0;y=1;z=1;
    #10;
    w=1;x=1;y=0;z=0;
    #10;
    w=1;x=1;y=0;z=1;
    #10;
    w=1;x=1;y=1;z=0;
    #10;
    w=1;x=1;y=1;z=1;
    #10;
end
initial begin
    $dumpfile("wave.vcd");//  iverilog c.v tb.v
    $dumpvars(0, tb); // vvp wave
end
endmodule

Verilog/midterm_ex5/wave.vcd
$date
	Fri Oct 31 17:50:47 2025
$end
$version
	Icarus Verilog
$end
$timescale
	1s
$end
$scope module tb $end
$var wire 1 ! f $end
$var reg 1 " w $end
$var reg 1 # x $end
$var reg 1 $ y $end
$var reg 1 % z $end
$scope module F $end
$var wire 1 & a $end
$var wire 1 ' b $end
$var wire 1 ( c $end
$var wire 1 ! f $end
$var wire 1 " w $end
$var wire 1 ) wn $end
$var wire 1 # x $end
$var wire 1 * xn $end
$var wire 1 $ y $end
$var wire 1 + yn $end
$var wire 1 % z $end
$var wire 1 , zn $end
$upscope $end
$upscope $end
$enddefinitions $end
$comment Show the parameter values. $end
$dumpall
$end
#0
$dumpvars
1,
1+
1*
1)
0(
0'
1&
0%
0$
0#
0"
1!
$end
#10
0!
0&
0,
1%
#20
1,
0+
0%
1$
#30
0,
1%
#40
1!
1&
1,
1+
0*
0%
0$
1#
#50
0&
0,
1'
1%
#60
0!
1,
0'
0+
0%
1$
#70
1!
0,
1'
1%
#80
1(
1!
1,
1+
1*
0'
0)
0%
0$
0#
1"
#90
0,
1%
#100
0!
0(
1,
0+
0%
1$
#110
0,
1%
#120
1,
1+
0*
0%
0$
1#
#130
1!
0,
1'
1%
#140
0!
1,
0'
0+
0%
1$
#150
1!
0,
1'
1%
