Verilog/bcd_7seg_behavior/BCDto7seg.v
module BCDto7seg ( //common-anode共陽 driven for 0
    input A,B,C,D, //A MSB
    output reg [7:0] out //a,b,c,d,e,f,g,dp
);
always@(A or B or C or D) begin
    case ({A,B,C,D})
        4'b0000: out = 8'b00000011;
        4'b0001: out = 8'b10011111;
        4'b0010: out = 8'b00100101;
        4'b0011: out = 8'b00001101;
        4'b0100: out = 8'b10011001;
        4'b0101: out = 8'b01001001;
        4'b0110: out = 8'b01000001;
        4'b0111: out = 8'b00011111;
        4'b1000: out = 8'b00000001;
        4'b1001: out = 8'b00001001;
        default: out = 8'b11111111;
    endcase
end
endmodule

Verilog/bcd_7seg_behavior/tb.v
module tb;
reg A,B,C,D; //A MSB
wire [7:0] out;;
BCDto7seg BCD(.A(A), .B(B), .C(C), .D(D), .out(out));
initial 
begin
 A = 0; B = 0; C = 0; D = 0;
 #10;
 A = 0; B = 0; C = 0; D = 1;
 #10;
 A = 0; B = 0; C = 1; D = 0;
 #10;
 A = 0; B = 0; C = 1; D = 1;
 #10;
 A = 0; B = 1; C = 0; D = 0;
 #10;
 A = 0; B = 1; C = 0; D = 1;
 #10;
 A = 0; B = 1; C = 1; D = 0;
 #10;
 A = 0; B = 1; C = 1; D = 1;
 #10;
 A = 1; B = 0; C = 0; D = 0;
 #10;
 A = 1; B = 0; C = 0; D = 1;
 #10;
end
initial begin
    $dumpfile("wave.vcd"); //  iverilog -o wave BCDto7seg.v tb.v
    $dumpvars(0, tb); // vvp wave
end
endmodule

Verilog/bcd_7seg_behavior/wave.vcd
$date
	Thu Oct 30 00:34:38 2025
$end
$version
	Icarus Verilog
$end
$timescale
	1s
$end
$scope module tb $end
$var wire 8 ! out [7:0] $end
$var reg 1 " A $end
$var reg 1 # B $end
$var reg 1 $ C $end
$var reg 1 % D $end
$scope module BCD $end
$var wire 1 " A $end
$var wire 1 # B $end
$var wire 1 $ C $end
$var wire 1 % D $end
$var reg 8 & out [7:0] $end
$upscope $end
$upscope $end
$enddefinitions $end
$comment Show the parameter values. $end
$dumpall
$end
#0
$dumpvars
b11 &
0%
0$
0#
0"
b11 !
$end
#10
b10011111 !
b10011111 &
1%
#20
b100101 !
b100101 &
0%
1$
#30
b1101 !
b1101 &
1%
#40
b10011001 !
b10011001 &
0%
0$
1#
#50
b1001001 !
b1001001 &
1%
#60
b1000001 !
b1000001 &
0%
1$
#70
b11111 !
b11111 &
1%
#80
b1 !
b1 &
0%
0$
0#
1"
#90
b1001 !
b1001 &
1%
