Verilog/Full_sub/full_sub_dataflow.v
module fullsub (
 input x,y,z,
 output d,b
);
assign d=((~x & ~y & z)|(~x & y & ~z)|(x & ~y & ~z)|(x & y & z));
assign b=((~x & y)|(~x & z)|(y & z));
endmodule

Verilog/Full_sub/tb_dataflow.v
module full_sub_tb; 
reg x,y,z;
wire d,b;
fullsub f(.d(d), .b(b), .x(x), .y(y), .z(z));
initial 
begin
    x=0;y=0;z=0;
    #10;
    x=0;y=0;z=1;
    #10;
    x=0;y=1;z=0;
    #10;
    x=0;y=1;z=1;
    #10;
    x=1;y=0;z=0;
    #10;
    x=1;y=0;z=1;
    #10;
    x=1;y=1;z=0;
    #10;
    x=1;y=1;z=1;
    #10;
end
initial begin
    $dumpfile("wave.vcd"); //  iverilog -o wave full_sub_dataflow.v tb_dataflow.v
    $dumpvars(0, full_sub_tb); // vvp wave
end
endmodule

Verilog/Full_sub/wave.vcd
$date
	Fri Oct 31 17:34:05 2025
$end
$version
	Icarus Verilog
$end
$timescale
	1s
$end
$scope module full_sub_tb $end
$var wire 1 ! d $end
$var wire 1 " b $end
$var reg 1 # x $end
$var reg 1 $ y $end
$var reg 1 % z $end
$scope module f $end
$var wire 1 " b $end
$var wire 1 ! d $end
$var wire 1 # x $end
$var wire 1 $ y $end
$var wire 1 % z $end
$upscope $end
$upscope $end
$enddefinitions $end
$comment Show the parameter values. $end
$dumpall
$end
#0
$dumpvars
0%
0$
0#
0"
0!
$end
#10
1!
1"
1%
#20
0%
1$
#30
0!
1%
#40
1!
0"
0%
0$
1#
#50
0!
1%
#60
0%
1$
#70
1!
1"
1%
