Verilog/ALU/ALU.v
module F_8_ALU(out, a, b, select);
output reg [5:0] out;
input [2:0] select;
input [3:0] a, b; //改成4bit輸入
reg [5:0] compare1, compare2; //1 -> max 2 -> min
always@(select)
begin
    if(a>b) //max
        compare1 = a;
    else 
        compare1 = b;
    if(a>b) //min
        compare2 = b;
    else 
        compare2 = a;
        
    case (select)
        3'b000: out = a;
        3'b001: out = a + b;
        3'b010: out = a - b;
        3'b011: out = a + 1; // 遞增
        3'b100: out = a - 1; // 遞減
        3'b101: out = compare1;
        3'b110: out = compare2;
        3'b111: out = (a+b)/2;
        default: out = 'bx;
    endcase
end
endmodule

Verilog/ALU/tb.v
module tb;
wire [5:0] out;
reg [2:0] select;
reg [3:0] a, b;
F_8_ALU alu (.out(out), .a(a), .b(b), .select(select));
initial begin
    a = 4; b =2; select = 7;
    for(integer i = 0;i <8;i = i + 1)
    begin
        select = select +1;
        #10;
    end
    $finish;
end
initial begin
    $dumpfile("wave.vcd"); //  iverilog -o wave ALU.v tb.v
    $dumpvars(0, tb); // vvp wave
end
endmodule

Verilog/ALU/wave.vcd
$date
	Thu Oct 30 01:34:59 2025
$end
$version
	Icarus Verilog
$end
$timescale
	1s
$end
$scope module tb $end
$var wire 6 ! out [5:0] $end
$var reg 4 " a [3:0] $end
$var reg 4 # b [3:0] $end
$var reg 3 $ select [2:0] $end
$scope module alu $end
$var wire 4 % a [3:0] $end
$var wire 4 & b [3:0] $end
$var wire 3 ' select [2:0] $end
$var reg 6 ( compare1 [5:0] $end
$var reg 6 ) compare2 [5:0] $end
$var reg 6 * out [5:0] $end
$upscope $end
$scope begin $ivl_for_loop0 $end
$var integer 32 + i [31:0] $end
$upscope $end
$upscope $end
$enddefinitions $end
$comment Show the parameter values. $end
$dumpall
$end
#0
$dumpvars
b0 +
b100 *
b10 )
b100 (
b0 '
b10 &
b100 %
b0 $
b10 #
b100 "
b100 !
$end
#10
b110 !
b110 *
b1 $
b1 '
b1 +
#20
b10 !
b10 *
b10 $
b10 '
b10 +
#30
b101 !
b101 *
b11 $
b11 '
b11 +
#40
b11 !
b11 *
b100 $
b100 '
b100 +
#50
b100 !
b100 *
b101 $
b101 '
b101 +
#60
b10 !
b10 *
b110 $
b110 '
b110 +
#70
b11 !
b11 *
b111 $
b111 '
b111 +
#80
b1000 +
