Verilog/ex2_1015/BCDto7seg.v
module BCDto7seg (
    input A,B,C,D, //A MSB
    output a,b,c,d,e,f,g
);
assign a = (B & ~C & ~D) | (~A & ~B & ~C & D);
assign b = (B & ~C & D) | (B & C & ~D);
assign c = ~B & C & ~D;
assign d = (B & ~C & ~D) | (B & C & D) | (~A & ~B & ~C & D);
assign e = D | (B & ~C);
assign f = (C & D) | (~B & C) | (~A & ~B & D);
assign g = (~A & ~B & ~C) | (B & C & D);

endmodule

Verilog/ex2_1015/tb.v
module tb;
reg A,B,C,D; //A MSB
wire a,b,c,d,e,f,g;
BCDto7seg BCD(.A(A), .B(B), .C(C), .D(D), .a(a), .b(b), .c(c), .d(d), .e(e), .f(f), .g(g));
initial 
begin
 A = 0; B = 0; C = 0; D = 0;
 #10;
 A = 0; B = 0; C = 0; D = 1;
 #10;
 A = 0; B = 0; C = 1; D = 0;
 #10;
 A = 0; B = 0; C = 1; D = 1;
 #10;
 A = 0; B = 1; C = 0; D = 0;
 #10;
 A = 0; B = 1; C = 0; D = 1;
 #10;
 A = 0; B = 1; C = 1; D = 0;
 #10;
 A = 0; B = 1; C = 1; D = 1;
 #10;
 A = 1; B = 0; C = 0; D = 0;
 #10;
 A = 1; B = 0; C = 0; D = 1;
 #10;
end
initial begin
    $dumpfile("wave.vcd"); //  iverilog -o wave BCDto7seg.v tb.v
    $dumpvars(0, tb); // vvp wave
end
endmodule

Verilog/ex2_1015/wave.vcd
$date
	Wed Oct 15 14:58:00 2025
$end
$version
	Icarus Verilog
$end
$timescale
	1s
$end
$scope module tb $end
$var wire 1 ! g $end
$var wire 1 " f $end
$var wire 1 # e $end
$var wire 1 $ d $end
$var wire 1 % c $end
$var wire 1 & b $end
$var wire 1 ' a $end
$var reg 1 ( A $end
$var reg 1 ) B $end
$var reg 1 * C $end
$var reg 1 + D $end
$scope module BCD $end
$var wire 1 ( A $end
$var wire 1 ) B $end
$var wire 1 * C $end
$var wire 1 + D $end
$var wire 1 ' a $end
$var wire 1 & b $end
$var wire 1 % c $end
$var wire 1 $ d $end
$var wire 1 # e $end
$var wire 1 " f $end
$var wire 1 ! g $end
$upscope $end
$upscope $end
$enddefinitions $end
$comment Show the parameter values. $end
$dumpall
$end
#0
$dumpvars
0+
0*
0)
0(
0'
0&
0%
0$
0#
0"
1!
$end
#10
1'
1$
1"
1#
1+
#20
0!
0'
0$
1%
0#
0+
1*
#30
0%
1#
1+
#40
1$
1'
0"
1#
0+
0*
1)
#50
0$
0'
1&
1+
#60
0#
0+
1*
#70
0&
1$
1"
1!
1#
1+
#80
0$
0"
0!
0#
0+
0*
0)
1(
#90
1#
1+
